rjsonnet-0.5.6.dist-info/METADATA
rjsonnet-0.5.6.dist-info/WHEEL
rjsonnet/__init__.py
rjsonnet/__init__.pyi
rjsonnet/py.typed
rjsonnet/rjsonnet.abi3.so
rjsonnet-0.5.6.dist-info/RECORD
