Metadata-Version: 2.4
Name: rjsonnet
Version: 0.5.6
Summary: Python bindings to Rust jrsonnet crate
Home-Page: https://github.com/messense/rjsonnet-py
Author: messense <messense@icloud.com>
Author-email: messense <messense@icloud.com>
License: MIT
Project-URL: Source Code, https://github.com/messense/rjsonnet-py.git
